kk593/p1.py
kk593-0.1.dist-info/METADATA
kk593-0.1.dist-info/WHEEL
kk593-0.1.dist-info/top_level.txt
kk593-0.1.dist-info/RECORD
