Metadata-Version: 2.1
Name: kk593
Version: 0.1
Summary: good mrng
Home-page: UNKNOWN
Author: Kamal Kumar
Author-email: kamalsir@ymail.com
License: UNKNOWN
Platform: UNKNOWN
